{
  "site": "Strong Mom Quotes",
  "domain": "https://strongmomquotes.com",
  "categories": [
    {
      "slug": "strong-mom-quotes",
      "title": "Strong Mom Quotes",
      "h1": "Strong Mom Quotes",
      "metaTitle": "50+ Strong Mom Quotes About Strength and Love (2026)",
      "metaDescription": "Original strong mom quotes about courage, resilience and love. Read them free, copy any quote, or turn it into a beautiful shareable card in seconds.",
      "intro": "Strength in motherhood rarely looks like the movies. It looks like showing up tired, loving hard on the difficult days, and starting again every morning. These original strong mom quotes were written to put words to that quiet power. Read them, copy your favorite, or turn any one of them into a beautiful card to share or keep.",
      "quotes": [
        {
          "text": "She carried the whole house on her shoulders and still made it feel light.",
          "by": "Strong Mom Quotes"
        },
        {
          "text": "A strong mom is not the one who never breaks. She is the one who rebuilds with the pieces.",
          "by": "Strong Mom Quotes"
        },
        {
          "text": "You are the calm your children borrow when the day is too loud.",
          "by": "Strong Mom Quotes"
        },
        {
          "text": "Her strength was never loud. It was the quiet decision, made daily, to keep going.",
          "by": "Strong Mom Quotes"
        },
        {
          "text": "Motherhood asked for everything she had. She answered with more than she knew she carried.",
          "by": "Strong Mom Quotes"
        },
        {
          "text": "A mother's courage is measured in ordinary mornings, not grand moments.",
          "by": "Strong Mom Quotes"
        },
        {
          "text": "She grows stronger in the exact places life tried to bend her.",
          "by": "Strong Mom Quotes"
        },
        {
          "text": "Behind every calm bedtime is a woman who fought a hundred small battles that day and won enough of them.",
          "by": "Strong Mom Quotes"
        },
        {
          "text": "Your children will not remember a perfect mother. They will remember a present one, and that takes more strength.",
          "by": "Strong Mom Quotes"
        },
        {
          "text": "She is soft with her children and unbreakable for them. Both at once. That is the job.",
          "by": "Strong Mom Quotes"
        },
        {
          "text": "Some heroes wear capes. Most reheat their coffee three times and keep going anyway.",
          "by": "Strong Mom Quotes"
        },
        {
          "text": "A mother's love is the only load that gets heavier and lighter at the same time.",
          "by": "Strong Mom Quotes"
        },
        {
          "text": "She did not find her strength in motherhood. Motherhood revealed the strength that was already there.",
          "by": "Strong Mom Quotes"
        },
        {
          "text": "On the days you feel weakest, look at what you carried anyway. That is strength.",
          "by": "Strong Mom Quotes"
        },
        {
          "text": "Little eyes are learning what strong looks like by watching you get back up.",
          "by": "Strong Mom Quotes"
        },
        {
          "text": "The bravest thing she does is done in secret: she believes in tomorrow on the nights she has nothing left.",
          "by": "Strong Mom Quotes"
        }
      ],
      "blurb": "the quiet, daily kind of courage"
    },
    {
      "slug": "short-mom-quotes",
      "title": "Short Mom Quotes",
      "h1": "Short Mom Quotes",
      "metaTitle": "40+ Short Mom Quotes: Sweet, Strong and Easy to Share",
      "metaDescription": "Short mom quotes that fit a caption, a card or a text message. Copy any quote free or turn it into a shareable quote card in one tap.",
      "intro": "Sometimes five words say more than five paragraphs. These short mom quotes are made for captions, cards, lock screens and quick messages to a mom who needs a lift today. Tap copy, or make any of them into a picture card in seconds.",
      "quotes": [
        {
          "text": "Mom: a title just above queen.",
          "by": "Strong Mom Quotes"
        },
        {
          "text": "Tired, but triumphant.",
          "by": "Strong Mom Quotes"
        },
        {
          "text": "She is the heartbeat of the house.",
          "by": "Strong Mom Quotes"
        },
        {
          "text": "Raising humans. Running on love.",
          "by": "Strong Mom Quotes"
        },
        {
          "text": "Strong is her default setting.",
          "by": "Strong Mom Quotes"
        },
        {
          "text": "Home is wherever mom is.",
          "by": "Strong Mom Quotes"
        },
        {
          "text": "Love, laundry, repeat.",
          "by": "Strong Mom Quotes"
        },
        {
          "text": "Small hands, whole heart.",
          "by": "Strong Mom Quotes"
        },
        {
          "text": "She makes ordinary days feel safe.",
          "by": "Strong Mom Quotes"
        },
        {
          "text": "One woman. A thousand quiet victories.",
          "by": "Strong Mom Quotes"
        },
        {
          "text": "Mothers turn houses into shelters.",
          "by": "Strong Mom Quotes"
        },
        {
          "text": "Fueled by coffee. Held together by love.",
          "by": "Strong Mom Quotes"
        },
        {
          "text": "Her lap was my first home.",
          "by": "Strong Mom Quotes"
        },
        {
          "text": "Still her baby. Just taller.",
          "by": "Strong Mom Quotes"
        },
        {
          "text": "Grace under pressure has a name: mom.",
          "by": "Strong Mom Quotes"
        }
      ],
      "blurb": "five words that fit any caption"
    },
    {
      "slug": "funny-mom-quotes",
      "title": "Funny Mom Quotes",
      "h1": "Funny Mom Quotes",
      "metaTitle": "40+ Funny Mom Quotes That Are Painfully True",
      "metaDescription": "Funny mom quotes about coffee, chaos and negotiating with tiny humans. Copy any quote free or turn it into a shareable card in one tap.",
      "intro": "Motherhood is beautiful, exhausting and occasionally ridiculous, sometimes all before breakfast. These funny mom quotes are for the moms who laugh so they do not cry into the laundry pile. Share one with a mom friend who gets it.",
      "quotes": [
        {
          "text": "I used to have functioning brain cells. Then I traded them for children.",
          "by": "Strong Mom Quotes"
        },
        {
          "text": "Motherhood: powered by cold coffee and questionable snacks found in the car.",
          "by": "Strong Mom Quotes"
        },
        {
          "text": "My children call it bedtime. I call it the nightly hostage negotiation.",
          "by": "Strong Mom Quotes"
        },
        {
          "text": "Silence is golden. Unless you have a toddler. Then silence is very, very suspicious.",
          "by": "Strong Mom Quotes"
        },
        {
          "text": "I run a small taxi service for people who never pay and always criticize the music.",
          "by": "Strong Mom Quotes"
        },
        {
          "text": "Being a mom means saying the sentence: do not lick your brother. Twice. Before nine a.m.",
          "by": "Strong Mom Quotes"
        },
        {
          "text": "My hobbies include reheating coffee and finding shoes that were in someone's hand ten seconds ago.",
          "by": "Strong Mom Quotes"
        },
        {
          "text": "Sleep like a baby, they said. My baby wakes up every forty minutes to check I still exist.",
          "by": "Strong Mom Quotes"
        },
        {
          "text": "I childproofed the house. The children still got in.",
          "by": "Strong Mom Quotes"
        },
        {
          "text": "You know you are a mom when hiding in the bathroom counts as a spa day.",
          "by": "Strong Mom Quotes"
        },
        {
          "text": "Dinner options tonight: take it or leave it.",
          "by": "Strong Mom Quotes"
        },
        {
          "text": "My child asked where I got my patience. I told him I was still waiting for it to be delivered.",
          "by": "Strong Mom Quotes"
        },
        {
          "text": "Motherhood is a constant loop of wondering what that smell is.",
          "by": "Strong Mom Quotes"
        },
        {
          "text": "I love all my children equally. Especially the one who is currently asleep.",
          "by": "Strong Mom Quotes"
        },
        {
          "text": "They say kids keep you young. Mine keep me caffeinated, which is basically the same thing.",
          "by": "Strong Mom Quotes"
        }
      ],
      "blurb": "the ridiculous side of the job"
    },
    {
      "slug": "single-mom-quotes",
      "title": "Single Mom Quotes",
      "h1": "Single Mom Quotes",
      "metaTitle": "40+ Single Mom Quotes About Strength and Courage",
      "metaDescription": "Single mom quotes that honor the women doing the work of two with the heart of one. Copy any quote free or make it into a beautiful card.",
      "intro": "A single mom carries two jobs, one heart and zero days off. These original single mom quotes are written to honor that, without pity and without cliches. If you are a single mom, these words are for you. If you love one, send her one today.",
      "quotes": [
        {
          "text": "She is the provider and the comfort, the discipline and the softness. Both parents live in her.",
          "by": "Strong Mom Quotes"
        },
        {
          "text": "A single mom does the work of two and somehow still saves the best of herself for her children.",
          "by": "Strong Mom Quotes"
        },
        {
          "text": "Nobody claps when she pays the bills, packs the lunches and shows up to everything alone. So this is the applause.",
          "by": "Strong Mom Quotes"
        },
        {
          "text": "Being a single mother means your hardest days have no understudy. You go on anyway.",
          "by": "Strong Mom Quotes"
        },
        {
          "text": "She was not given an easy road, so she became the kind of woman who does not need one.",
          "by": "Strong Mom Quotes"
        },
        {
          "text": "One pair of hands, one tired heart, one entire childhood held safely together.",
          "by": "Strong Mom Quotes"
        },
        {
          "text": "Her children will grow up and understand: she was not just their mother. She was the whole team.",
          "by": "Strong Mom Quotes"
        },
        {
          "text": "A single mom's love is not half of anything. It is double everything.",
          "by": "Strong Mom Quotes"
        },
        {
          "text": "She learned to be the calm in the storm because there was no one else to be it.",
          "by": "Strong Mom Quotes"
        },
        {
          "text": "Every night she balances the books, the worries and the bedtime stories. Alone. And still gently.",
          "by": "Strong Mom Quotes"
        },
        {
          "text": "Raising children alone did not harden her heart. It proved how strong a soft heart can be.",
          "by": "Strong Mom Quotes"
        },
        {
          "text": "To the single moms: you are not doing it wrong because it is hard. It is hard because you are doing all of it.",
          "by": "Strong Mom Quotes"
        },
        {
          "text": "She built a childhood out of half the resources and twice the love.",
          "by": "Strong Mom Quotes"
        },
        {
          "text": "Some day her children will tell their children about her. That is the pension of a single mom, and it is enormous.",
          "by": "Strong Mom Quotes"
        },
        {
          "text": "Alone is where she worked. Loved is how her children grew.",
          "by": "Strong Mom Quotes"
        }
      ],
      "blurb": "for the woman doing the work of two"
    },
    {
      "slug": "working-mom-quotes",
      "title": "Working Mom Quotes",
      "h1": "Working Mom Quotes",
      "metaTitle": "40+ Working Mom Quotes About Balance and Grit",
      "metaDescription": "Working mom quotes about the juggle, the guilt and the grit. Copy any quote free or turn it into a shareable quote card in seconds.",
      "intro": "The working mom lives two full lives before dinner. These quotes are for the school run before the standup meeting, the emails answered from the pediatrician's waiting room, and the love that powers all of it. Copy one for a colleague, a friend, or your own desk.",
      "quotes": [
        {
          "text": "She closes her laptop and opens her arms, and both jobs get her whole heart.",
          "by": "Strong Mom Quotes"
        },
        {
          "text": "A working mom does not balance work and family. She carries both, and that is stronger.",
          "by": "Strong Mom Quotes"
        },
        {
          "text": "Somewhere between the meeting and the school gate, she became unstoppable.",
          "by": "Strong Mom Quotes"
        },
        {
          "text": "Her children are watching her build a life. That is not time away from them. That is a lesson for them.",
          "by": "Strong Mom Quotes"
        },
        {
          "text": "She answers to a boss all day and a tiny board of directors all night.",
          "by": "Strong Mom Quotes"
        },
        {
          "text": "Working mom guilt is proof of love in both directions. Let it point, not punish.",
          "by": "Strong Mom Quotes"
        },
        {
          "text": "The same hands that type the reports tie the shoelaces. Do not underestimate those hands.",
          "by": "Strong Mom Quotes"
        },
        {
          "text": "She is not half a mother and half a professional. She is fully both, which makes her twice as much.",
          "by": "Strong Mom Quotes"
        },
        {
          "text": "Every promotion she earns, she earns twice: once at work and once at home the same day.",
          "by": "Strong Mom Quotes"
        },
        {
          "text": "Some days work wins, some days home wins. Every day her children win, because she keeps showing up to both.",
          "by": "Strong Mom Quotes"
        },
        {
          "text": "Behind many great careers is a woman who also knows every word of a bedtime story by heart.",
          "by": "Strong Mom Quotes"
        },
        {
          "text": "She commutes between two worlds daily and is the sun in both of them.",
          "by": "Strong Mom Quotes"
        },
        {
          "text": "A working mother is a masterclass in priorities taught at full speed.",
          "by": "Strong Mom Quotes"
        },
        {
          "text": "The out of office reply is on, but a mother is never off duty. Respect the double shift.",
          "by": "Strong Mom Quotes"
        },
        {
          "text": "Her calendar is full. Her heart is fuller.",
          "by": "Strong Mom Quotes"
        }
      ],
      "blurb": "the double shift, honoured properly"
    },
    {
      "slug": "new-mom-quotes",
      "title": "New Mom Quotes",
      "h1": "New Mom Quotes",
      "metaTitle": "40+ New Mom Quotes for the Beautiful, Blurry First Year",
      "metaDescription": "New mom quotes about first days, sleepless nights and brand new love. Copy any quote free or turn it into a beautiful shareable card.",
      "intro": "Nothing prepares you for the first year: the love, the fog, the three a.m. feeds, the way your whole world reorganizes around one small person. These new mom quotes are for the beautiful blur. Send one to a new mom, or save one for yourself.",
      "quotes": [
        {
          "text": "The day her baby was born, a mother was born too, and both of them are still learning.",
          "by": "Strong Mom Quotes"
        },
        {
          "text": "Nobody tells you the nights are so long and the year is so short.",
          "by": "Strong Mom Quotes"
        },
        {
          "text": "You have known this child a few weeks and already you cannot remember who you were without them.",
          "by": "Strong Mom Quotes"
        },
        {
          "text": "New mom, you are not behind. There is no schedule. There is only the two of you, figuring it out together.",
          "by": "Strong Mom Quotes"
        },
        {
          "text": "At three in the morning it feels endless. One day these will be the nights you miss.",
          "by": "Strong Mom Quotes"
        },
        {
          "text": "Your baby does not need a perfect mother. Your baby needs you, and already loves you completely.",
          "by": "Strong Mom Quotes"
        },
        {
          "text": "The house is a mess and the baby is fed and held. You are doing this exactly right.",
          "by": "Strong Mom Quotes"
        },
        {
          "text": "A newborn takes everything you have and repays it with one small smile. Somehow the math works.",
          "by": "Strong Mom Quotes"
        },
        {
          "text": "She counts fingers, counts toes, counts breaths in the dark. New love keeps careful accounts.",
          "by": "Strong Mom Quotes"
        },
        {
          "text": "Ask for help. It is not a weakness. It is how mothers have raised babies since the beginning.",
          "by": "Strong Mom Quotes"
        },
        {
          "text": "Every mother in history started exactly where you are: unsure, exhausted and utterly in love.",
          "by": "Strong Mom Quotes"
        },
        {
          "text": "You will fold the tiny clothes a hundred times and one day they will suddenly be too small. Take the photo now.",
          "by": "Strong Mom Quotes"
        },
        {
          "text": "The first year rewrites you. Be patient with the woman being rewritten.",
          "by": "Strong Mom Quotes"
        },
        {
          "text": "You grew a person. Growing into their mother is allowed to take a little time.",
          "by": "Strong Mom Quotes"
        },
        {
          "text": "One tiny hand around your finger, and your heart signed a contract with no end date.",
          "by": "Strong Mom Quotes"
        }
      ],
      "blurb": "for the beautiful, sleepless blur"
    },
    {
      "slug": "boy-mom-quotes",
      "title": "Boy Mom Quotes",
      "h1": "Boy Mom Quotes",
      "metaTitle": "40+ Boy Mom Quotes About Raising Sons With Love",
      "metaDescription": "Boy mom quotes about muddy shoes, big hearts and raising good men. Copy any quote free or make it into a shareable quote card.",
      "intro": "Raising boys means muddy footprints, superhero capes at the supermarket and a love that tackles you at full speed. These boy mom quotes celebrate the loud, tender, wonderful work of raising sons and the mothers shaping good men one bedtime at a time.",
      "quotes": [
        {
          "text": "She is raising a boy, which means she is raising the man some family will one day be grateful for.",
          "by": "Strong Mom Quotes"
        },
        {
          "text": "A boy mom's house is louder, muddier and somehow fuller of flowers picked from the neighbor's garden.",
          "by": "Strong Mom Quotes"
        },
        {
          "text": "Sons grow tall, but they never grow out of needing their mother's voice.",
          "by": "Strong Mom Quotes"
        },
        {
          "text": "Teach him to be brave and gentle, and you have given the world a good man.",
          "by": "Strong Mom Quotes"
        },
        {
          "text": "He will not remember the spotless floors. He will remember that you played on them.",
          "by": "Strong Mom Quotes"
        },
        {
          "text": "A mother is her son's first hero and his standard for kindness.",
          "by": "Strong Mom Quotes"
        },
        {
          "text": "Boy moms speak fluent dinosaur, referee wrestling matches and heal all wounds with one kiss.",
          "by": "Strong Mom Quotes"
        },
        {
          "text": "One day his hugs will come from shoulders taller than yours. He learned those hugs from you.",
          "by": "Strong Mom Quotes"
        },
        {
          "text": "The little boy who brings you rocks and worms is bringing you his whole heart. Accept the worms.",
          "by": "Strong Mom Quotes"
        },
        {
          "text": "Raising a boy is loud work with a quiet reward: the kind man he becomes.",
          "by": "Strong Mom Quotes"
        },
        {
          "text": "She kisses scraped knees now so he will know how to be tender later.",
          "by": "Strong Mom Quotes"
        },
        {
          "text": "A son's first love story is simple: his mother showed up, every single day.",
          "by": "Strong Mom Quotes"
        },
        {
          "text": "Mud washes out. The memory of a mother who said yes to the puddles never does.",
          "by": "Strong Mom Quotes"
        },
        {
          "text": "To the mom of boys: the noise is temporary. The character you are building is not.",
          "by": "Strong Mom Quotes"
        },
        {
          "text": "Somewhere under the toy trucks and odd socks, a good man is under construction. You are the foreman.",
          "by": "Strong Mom Quotes"
        }
      ],
      "blurb": "mud, noise and the good man being built"
    },
    {
      "slug": "girl-mom-quotes",
      "title": "Girl Mom Quotes",
      "h1": "Girl Mom Quotes",
      "metaTitle": "40+ Girl Mom Quotes About Raising Daughters",
      "metaDescription": "Girl mom quotes about raising brave, kind daughters and the bond between mothers and girls. Copy free or make a shareable card.",
      "intro": "Raising a daughter means watching a smaller version of your own heart walk around in glittery shoes. These girl mom quotes are about that bond: the braids and the big feelings, the example you set without knowing it, and the woman she is quietly becoming.",
      "quotes": [
        {
          "text": "She is not just raising a daughter. She is raising the woman her granddaughters will tell stories about.",
          "by": "Strong Mom Quotes"
        },
        {
          "text": "A daughter learns what her voice is worth by hearing how her mother uses hers.",
          "by": "Strong Mom Quotes"
        },
        {
          "text": "Braids, big feelings and boundless questions: the beautiful weather of raising girls.",
          "by": "Strong Mom Quotes"
        },
        {
          "text": "Your daughter is watching how you speak to yourself. Speak kindly. She is taking notes.",
          "by": "Strong Mom Quotes"
        },
        {
          "text": "First her hand fits in yours. Then her shoes fit yours. Then, one astonishing day, her strength matches yours.",
          "by": "Strong Mom Quotes"
        },
        {
          "text": "Raise her brave first. The world will try to teach her small; make sure you got there before it.",
          "by": "Strong Mom Quotes"
        },
        {
          "text": "A mother and daughter are two chapters of the same story, reading each other.",
          "by": "Strong Mom Quotes"
        },
        {
          "text": "Teach your daughter that kind and strong are not opposites. Show her by being both.",
          "by": "Strong Mom Quotes"
        },
        {
          "text": "The tea parties are practice. One day she will pour her courage the way you poured yours.",
          "by": "Strong Mom Quotes"
        },
        {
          "text": "She borrows your shoes today. She has been borrowing your courage all along.",
          "by": "Strong Mom Quotes"
        },
        {
          "text": "A girl mom's greatest work is invisible: the confidence stitched quietly into her daughter every day.",
          "by": "Strong Mom Quotes"
        },
        {
          "text": "Someday she will face something hard and hear your voice inside her own. Make it a kind one.",
          "by": "Strong Mom Quotes"
        },
        {
          "text": "Between mothers and daughters there is a language older than words.",
          "by": "Strong Mom Quotes"
        },
        {
          "text": "You are her first mirror. Reflect back the strong, lovely girl she really is.",
          "by": "Strong Mom Quotes"
        },
        {
          "text": "Little girls with big dreams become women with vision, especially when their mother believed first.",
          "by": "Strong Mom Quotes"
        }
      ],
      "blurb": "the bond and the example you are setting"
    },
    {
      "slug": "tired-mom-quotes",
      "title": "Tired Mom Quotes",
      "h1": "Tired Mom Quotes",
      "metaTitle": "40+ Tired Mom Quotes for the Hard, Heavy Days",
      "metaDescription": "Tired mom quotes for exhausted mothers who keep going anyway. Honest, warm words you can copy free or turn into a shareable card.",
      "intro": "Some days motherhood is heavy and the tank is empty and bedtime feels a decade away. These tired mom quotes are for those days: honest words that see the exhaustion and still hand you a little light. You are more than the tiredness. These quotes remember that for you.",
      "quotes": [
        {
          "text": "She is tired in her bones and still gentle with her hands. That is a kind of heroism.",
          "by": "Strong Mom Quotes"
        },
        {
          "text": "Being exhausted and still showing up is not failing. It is the very definition of showing up.",
          "by": "Strong Mom Quotes"
        },
        {
          "text": "Tonight you are tired because today you were needed. Both things are true, and one of them is beautiful.",
          "by": "Strong Mom Quotes"
        },
        {
          "text": "Even on the days she runs on empty, her children run on her love. Somehow there is always fuel for that.",
          "by": "Strong Mom Quotes"
        },
        {
          "text": "Rest is not a reward you must earn, mama. It is a repair you are owed.",
          "by": "Strong Mom Quotes"
        },
        {
          "text": "You did not lose your patience today because you are a bad mother. You ran out because you gave it all away.",
          "by": "Strong Mom Quotes"
        },
        {
          "text": "The dishes can wait. The tired woman holding this phone cannot. Sit down for five minutes.",
          "by": "Strong Mom Quotes"
        },
        {
          "text": "Some days the victory is simply this: everyone was loved and everyone was fed. Take the win.",
          "by": "Strong Mom Quotes"
        },
        {
          "text": "A tired mom is not a weak mom. She is a strong one who has been strong too long without help.",
          "by": "Strong Mom Quotes"
        },
        {
          "text": "You comfort everyone in this house. Consider this your reminder that you count as someone too.",
          "by": "Strong Mom Quotes"
        },
        {
          "text": "The exhaustion is real. So is the fact that you are somebody's whole safe world.",
          "by": "Strong Mom Quotes"
        },
        {
          "text": "Go to bed, mama. The to-do list is lying to you about what matters.",
          "by": "Strong Mom Quotes"
        },
        {
          "text": "Hard days do not mean you are doing it wrong. They mean you are doing it, which is more than it looks like.",
          "by": "Strong Mom Quotes"
        },
        {
          "text": "One day at a time is not a small plan. Some seasons, it is the bravest plan there is.",
          "by": "Strong Mom Quotes"
        },
        {
          "text": "Tomorrow you will be somebody's sunshine again. Tonight, let yourself be tired without guilt.",
          "by": "Strong Mom Quotes"
        }
      ],
      "blurb": "honest words for an empty tank"
    },
    {
      "slug": "encouraging-quotes-for-moms",
      "title": "Encouraging Quotes for Moms",
      "h1": "Encouraging Quotes for Moms",
      "metaTitle": "40+ Encouraging Quotes for Moms Who Need a Lift Today",
      "metaDescription": "Encouraging quotes for moms who are doubting themselves. Warm, original words of support to copy free or turn into a shareable card.",
      "intro": "Every mom doubts herself sometimes. It is the tax on caring this much. These encouraging quotes for moms are the words a good friend would say over coffee: you are doing better than you think, the love is landing, and the hard seasons pass. Send one to a mom who needs it, including yourself.",
      "quotes": [
        {
          "text": "You are doing better than you think. Doubt just gets louder in a quiet house at night.",
          "by": "Strong Mom Quotes"
        },
        {
          "text": "The love you pour in is landing, even on the days you cannot see where it went.",
          "by": "Strong Mom Quotes"
        },
        {
          "text": "Your children got exactly the mother they needed. It has been you all along.",
          "by": "Strong Mom Quotes"
        },
        {
          "text": "You are allowed to be a masterpiece and a work in progress at the same time. Every mother is.",
          "by": "Strong Mom Quotes"
        },
        {
          "text": "Look how far you have carried this family. Now say one kind thing to the woman who carried it.",
          "by": "Strong Mom Quotes"
        },
        {
          "text": "Good mothers worry they are not good mothers. The worrying is the proof.",
          "by": "Strong Mom Quotes"
        },
        {
          "text": "Nobody sees everything you do. But everything you do is quietly building people. Keep going.",
          "by": "Strong Mom Quotes"
        },
        {
          "text": "This season is heavy, not endless. You have outlasted every hard season so far. Your record is perfect.",
          "by": "Strong Mom Quotes"
        },
        {
          "text": "You do not have to be everything today. Being there is already most of it.",
          "by": "Strong Mom Quotes"
        },
        {
          "text": "Somewhere in the mess of today, you did a hundred loving things without noticing. Your children noticed.",
          "by": "Strong Mom Quotes"
        },
        {
          "text": "Comparison will show you every mother's highlight reel and none of their laundry. Close the app. You are enough.",
          "by": "Strong Mom Quotes"
        },
        {
          "text": "Small, steady love changes lives. Yours is the steadiest love in the building.",
          "by": "Strong Mom Quotes"
        },
        {
          "text": "One day your grown children will describe their childhood, and you will finally hear how well you did.",
          "by": "Strong Mom Quotes"
        },
        {
          "text": "You have never done this exact day with these exact children before. Be as patient with yourself as you are with them.",
          "by": "Strong Mom Quotes"
        },
        {
          "text": "Mama, the fact that you are trying this hard means it is going to be okay.",
          "by": "Strong Mom Quotes"
        }
      ],
      "blurb": "the friend who tells you it is landing"
    },
    {
      "slug": "mom-quotes-from-daughter",
      "title": "Mom Quotes from Daughter",
      "h1": "Mom Quotes from Daughter",
      "metaTitle": "40+ Mom Quotes from Daughter: I Love You Mom Quotes",
      "metaDescription": "Beautiful mom quotes from a daughter for birthdays, Mother's Day or any day. Copy any quote free or turn it into a card she can keep.",
      "intro": "Looking for the right words to tell your mom what she means to you? These mom quotes from a daughter say the things we feel but rarely find words for. Perfect for a birthday card, a Mother's Day message, or a random Tuesday text that will make her whole week.",
      "quotes": [
        {
          "text": "Mom, everything soft and strong in me, I learned by watching you.",
          "by": "Strong Mom Quotes"
        },
        {
          "text": "The older I get, the more I realize my mother was right about nearly everything, including me.",
          "by": "Strong Mom Quotes"
        },
        {
          "text": "You were my first home, my first friend and my first example of what love looks like on its feet.",
          "by": "Strong Mom Quotes"
        },
        {
          "text": "I hear your voice in my kindest thoughts. Thank you for putting it there.",
          "by": "Strong Mom Quotes"
        },
        {
          "text": "Now that I am grown, I finally see it: all those ordinary days were you giving me everything.",
          "by": "Strong Mom Quotes"
        },
        {
          "text": "Mom, you clapped for me before I did anything worth clapping for. That is why I dared to try.",
          "by": "Strong Mom Quotes"
        },
        {
          "text": "Half of who I am is you. It is my favorite half.",
          "by": "Strong Mom Quotes"
        },
        {
          "text": "You held my hand until I could walk, then held my heart while I walked away, then welcomed me home every time.",
          "by": "Strong Mom Quotes"
        },
        {
          "text": "The strongest woman I know calls me her greatest achievement. Mom, you are mine.",
          "by": "Strong Mom Quotes"
        },
        {
          "text": "I used to roll my eyes at your advice. Now I give it to my friends, word for word.",
          "by": "Strong Mom Quotes"
        },
        {
          "text": "However old I get, some part of me will always be a little girl looking for you in a crowd.",
          "by": "Strong Mom Quotes"
        },
        {
          "text": "You taught me to be brave by never letting me see how scared you were.",
          "by": "Strong Mom Quotes"
        },
        {
          "text": "There are not enough Mother's Days in a lifetime to thank you properly. So I will just keep trying.",
          "by": "Strong Mom Quotes"
        },
        {
          "text": "Mom, if I become half the woman you are, my daughter will be lucky.",
          "by": "Strong Mom Quotes"
        },
        {
          "text": "Every good thing I do carries your fingerprints.",
          "by": "Strong Mom Quotes"
        }
      ],
      "blurb": "the words for her birthday card"
    },
    {
      "slug": "affirmations-for-moms",
      "title": "Affirmations for Moms",
      "h1": "Affirmations for Moms",
      "metaTitle": "40+ Daily Affirmations for Moms: Calm, Strong, Enough",
      "metaDescription": "Original daily affirmations for moms to start the day calm and strong. Read them free, copy any affirmation or turn it into a beautiful card.",
      "intro": "An affirmation is a small sentence you say to yourself until you believe it. These daily affirmations for moms were written for real mornings: the rushed ones, the tired ones, the ones where you need to hear that you are enough. Read one aloud, copy one to your notes, or make one into a card for your mirror or lock screen.",
      "quotes": [
        {
          "text": "I am the mother my children need, exactly as I am today.",
          "by": "Strong Mom Quotes"
        },
        {
          "text": "I am allowed to rest without earning it first.",
          "by": "Strong Mom Quotes"
        },
        {
          "text": "My love is doing more good than my worry can see.",
          "by": "Strong Mom Quotes"
        },
        {
          "text": "I am patient with my children and with myself.",
          "by": "Strong Mom Quotes"
        },
        {
          "text": "I release the standard of perfect and choose the standard of present.",
          "by": "Strong Mom Quotes"
        },
        {
          "text": "My home is built on love, not on tidiness.",
          "by": "Strong Mom Quotes"
        },
        {
          "text": "I am raising good humans, one ordinary day at a time.",
          "by": "Strong Mom Quotes"
        },
        {
          "text": "I trust myself to know my children better than any opinion online.",
          "by": "Strong Mom Quotes"
        },
        {
          "text": "Today I will speak to myself the way I speak to my children: kindly.",
          "by": "Strong Mom Quotes"
        },
        {
          "text": "I am strong enough for this day, and only this day is asked of me.",
          "by": "Strong Mom Quotes"
        },
        {
          "text": "Asking for help is one of my parenting skills.",
          "by": "Strong Mom Quotes"
        },
        {
          "text": "I am more than the tasks I complete.",
          "by": "Strong Mom Quotes"
        },
        {
          "text": "My best is enough, even on the days my best looks smaller.",
          "by": "Strong Mom Quotes"
        },
        {
          "text": "I choose progress in this house, not perfection.",
          "by": "Strong Mom Quotes"
        },
        {
          "text": "I am the safe place, and I deserve one too.",
          "by": "Strong Mom Quotes"
        }
      ],
      "blurb": "short sentences to say out loud each morning"
    },
    {
      "slug": "single-mom-affirmations",
      "title": "Single Mom Affirmations",
      "h1": "Single Mom Affirmations",
      "metaTitle": "40+ Single Mom Affirmations for Strength and Peace",
      "metaDescription": "Original affirmations for single moms doing the work of two. Read them free, copy any affirmation or turn it into a beautiful shareable card.",
      "intro": "When you are the only adult in the house, the voice you use with yourself matters twice as much. These single mom affirmations are for the woman holding it all: words of strength, permission and pride to carry through the day. Save the ones that land, and let them speak back to you when the day gets loud.",
      "quotes": [
        {
          "text": "I am doing the work of two with one heart, and my heart is enough.",
          "by": "Strong Mom Quotes"
        },
        {
          "text": "I am building a childhood my children will feel safe inside.",
          "by": "Strong Mom Quotes"
        },
        {
          "text": "I make hard decisions alone, and I make them with love.",
          "by": "Strong Mom Quotes"
        },
        {
          "text": "My family is whole because love makes it whole.",
          "by": "Strong Mom Quotes"
        },
        {
          "text": "I am allowed to be tired and still be proud.",
          "by": "Strong Mom Quotes"
        },
        {
          "text": "Every bill paid, every lunch packed, every story read: I did that.",
          "by": "Strong Mom Quotes"
        },
        {
          "text": "I am my children's steady ground, and I am steadier than I feel.",
          "by": "Strong Mom Quotes"
        },
        {
          "text": "I release guilt for what I cannot give and honor everything I do give.",
          "by": "Strong Mom Quotes"
        },
        {
          "text": "I am raising resilient children by showing them resilience daily.",
          "by": "Strong Mom Quotes"
        },
        {
          "text": "My strength today is my children's example tomorrow.",
          "by": "Strong Mom Quotes"
        },
        {
          "text": "I am not behind in life. I am carrying more and still moving.",
          "by": "Strong Mom Quotes"
        },
        {
          "text": "I accept help without shame, because strong is not the same as alone.",
          "by": "Strong Mom Quotes"
        },
        {
          "text": "I am the calm and the courage in this house.",
          "by": "Strong Mom Quotes"
        },
        {
          "text": "One pair of hands, one determined heart, one beautiful family.",
          "by": "Strong Mom Quotes"
        },
        {
          "text": "I am enough parent for this family. I always have been.",
          "by": "Strong Mom Quotes"
        }
      ],
      "blurb": "strength to carry through the day, alone"
    },
    {
      "slug": "new-mom-affirmations",
      "title": "New Mom Affirmations",
      "h1": "New Mom Affirmations",
      "metaTitle": "40+ New Mom Affirmations for the First Year",
      "metaDescription": "Gentle affirmations for new moms in the newborn fog. Read them free, copy any affirmation or turn it into a card for your mirror or lock screen.",
      "intro": "The first year of motherhood is tender and disorienting, and the voice in your head can turn harsh when you are running on broken sleep. These new mom affirmations are gentle corrections: true sentences to say over the crib, in the night feeds, and in front of the mirror. You are doing better than the fog lets you see.",
      "quotes": [
        {
          "text": "I am learning my baby, and my baby is learning me. We have time.",
          "by": "Strong Mom Quotes"
        },
        {
          "text": "I am the right mother for this child.",
          "by": "Strong Mom Quotes"
        },
        {
          "text": "My body did something extraordinary, and it deserves my kindness.",
          "by": "Strong Mom Quotes"
        },
        {
          "text": "I do not need to know everything today. I only need to love today.",
          "by": "Strong Mom Quotes"
        },
        {
          "text": "It is safe to ask for help. Mothers were never meant to do this alone.",
          "by": "Strong Mom Quotes"
        },
        {
          "text": "Every feed, every cuddle, every small win counts, even the ones nobody sees.",
          "by": "Strong Mom Quotes"
        },
        {
          "text": "I am allowed to miss my old life and love my new one at the same time.",
          "by": "Strong Mom Quotes"
        },
        {
          "text": "My baby does not compare me to anyone. Neither should I.",
          "by": "Strong Mom Quotes"
        },
        {
          "text": "This hard night will pass, and I will still be a good mother in the morning.",
          "by": "Strong Mom Quotes"
        },
        {
          "text": "I trust my instincts. They are wiser than my doubts.",
          "by": "Strong Mom Quotes"
        },
        {
          "text": "A fed baby, a held baby, a loved baby: I am doing this right.",
          "by": "Strong Mom Quotes"
        },
        {
          "text": "I am becoming a mother at exactly the pace I should.",
          "by": "Strong Mom Quotes"
        },
        {
          "text": "Slow days with my baby are not wasted days.",
          "by": "Strong Mom Quotes"
        },
        {
          "text": "I give myself the same grace I give this brand new person.",
          "by": "Strong Mom Quotes"
        },
        {
          "text": "I am tired, I am learning, and I am exactly what my baby needs.",
          "by": "Strong Mom Quotes"
        }
      ],
      "blurb": "gentle corrections for the newborn fog"
    },
    {
      "slug": "working-mom-affirmations",
      "title": "Working Mom Affirmations",
      "h1": "Working Mom Affirmations",
      "metaTitle": "40+ Working Mom Affirmations for the Double Shift",
      "metaDescription": "Affirmations for working moms balancing career and family. Read them free, copy any affirmation or turn it into a card for your desk.",
      "intro": "The working mom runs a double shift, and guilt loves a busy woman. These working mom affirmations push back: true sentences about ambition, presence and enoughness to read on the commute, before the big meeting, or at the kitchen table after bedtime. Put one on a card by your desk and let it argue with the guilt for you.",
      "quotes": [
        {
          "text": "I am showing my children what dedication looks like.",
          "by": "Strong Mom Quotes"
        },
        {
          "text": "I can love my work and love my family without apology.",
          "by": "Strong Mom Quotes"
        },
        {
          "text": "I am present where I am: at my desk, at the dinner table, in this moment.",
          "by": "Strong Mom Quotes"
        },
        {
          "text": "My children are not harmed by my ambition. They are inspired by it.",
          "by": "Strong Mom Quotes"
        },
        {
          "text": "I do two important jobs, and I am allowed to be proud of both.",
          "by": "Strong Mom Quotes"
        },
        {
          "text": "I release the guilt that asks me to be in two places at once.",
          "by": "Strong Mom Quotes"
        },
        {
          "text": "Providing for my family is an act of love.",
          "by": "Strong Mom Quotes"
        },
        {
          "text": "I am building a future and a childhood at the same time.",
          "by": "Strong Mom Quotes"
        },
        {
          "text": "Some days lean work, some days lean home. Every day leans love.",
          "by": "Strong Mom Quotes"
        },
        {
          "text": "I am allowed to close the laptop. The work will keep. The moment will not.",
          "by": "Strong Mom Quotes"
        },
        {
          "text": "My worth is not measured in a perfectly balanced day.",
          "by": "Strong Mom Quotes"
        },
        {
          "text": "I bring my whole heart to both of my worlds.",
          "by": "Strong Mom Quotes"
        },
        {
          "text": "I am teaching my children that women build things.",
          "by": "Strong Mom Quotes"
        },
        {
          "text": "Rest is part of my job description too.",
          "by": "Strong Mom Quotes"
        },
        {
          "text": "I am doing enough, at work and at home, even when it feels like neither.",
          "by": "Strong Mom Quotes"
        }
      ],
      "blurb": "the argument that answers the guilt"
    },
    {
      "slug": "classic-mom-quotes",
      "title": "Classic Mom Quotes",
      "h1": "Classic Mom Quotes from Literature and History",
      "metaTitle": "Classic Mom Quotes from Literature and History (Verified Sources)",
      "metaDescription": "Timeless quotes about mothers from classic literature, poetry and proverbs, each with a verified public domain source. Copy free or make a card.",
      "intro": "The love of mothers has been written about for as long as anyone has been writing. Every quote on this page comes from classic literature, poetry or traditional proverb, with the real source named, because a beautiful quote deserves an honest attribution. No invented celebrity quotes here, only the genuine article.",
      "quotes": [
        {
          "text": "I am angry nearly every day of my life, but I have learned not to show it; and I still hope to learn not to feel it.",
          "by": "Louisa May Alcott, Little Women (1868), spoken by Marmee"
        },
        {
          "text": "Mother is the name for God in the lips and hearts of little children.",
          "by": "William Makepeace Thackeray, Vanity Fair (1848)"
        },
        {
          "text": "A mother is a mother still, the holiest thing alive.",
          "by": "Samuel Taylor Coleridge, The Three Graves (1798)"
        },
        {
          "text": "If I were hanged on the highest hill, I know whose love would follow me still. Mother o' mine.",
          "by": "Rudyard Kipling, Mother o' Mine (1891)"
        },
        {
          "text": "Who ran to help me when I fell, and would some pretty story tell, or kiss the place to make it well? My mother.",
          "by": "Ann Taylor, My Mother (1804)"
        },
        {
          "text": "The hand that rocks the cradle is the hand that rules the world.",
          "by": "William Ross Wallace, poem title and refrain (1865)"
        },
        {
          "text": "All that I am, or hope to be, I owe to my angel mother.",
          "by": "Attributed to Abraham Lincoln by his biographer William Herndon"
        },
        {
          "text": "Strength and dignity are her clothing. She laughs at the time to come.",
          "by": "Proverbs 31:25, World English Bible (public domain translation)"
        },
        {
          "text": "God could not be everywhere, and therefore he made mothers.",
          "by": "Traditional proverb"
        },
        {
          "text": "An ounce of mother is worth a pound of clergy.",
          "by": "Traditional Spanish proverb"
        }
      ],
      "blurb": "lines from literature, with real sources"
    }
  ]
}